<?xml version="1.0" encoding="utf-8"?>
<xml>
  <Scripts>
    <Script>Ados Pakistan Limited.  </Script>
    <Price> 29</Price>
  </Scripts>
  <Scripts>
    <Script>Agha Steel Industries Ltd.  </Script>
    <Price> 15.80</Price>
  </Scripts>
  <Scripts>
    <Script>Aisha Steel Mills Limited.  </Script>
    <Price> 10.02</Price>
  </Scripts>
  <Scripts>
    <Script>Amreli Steels Limited.  </Script>
    <Price> 27.59</Price>
  </Scripts>
  <Scripts>
    <Script>Beco Steel Limited  </Script>
    <Price> 12.81</Price>
  </Scripts>
  <Scripts>
    <Script>Bolan Casting Ltd.  </Script>
    <Price> 42.09</Price>
  </Scripts>
  <Scripts>
    <Script>Crescent Steel &amp; Allied Product.  </Script>
    <Price> 37.04</Price>
  </Scripts>
  <Scripts>
    <Script>Dost Steels Ltd. [ DEFAULTER SEGMENT ] </Script>
    <Price> 6.25</Price>
  </Scripts>
  <Scripts>
    <Script>Huffaz Seamless Pipe Industries. [ DEFAULTER SEGMENT ] </Script>
    <Price> 10.26</Price>
  </Scripts>
  <Scripts>
    <Script>International Industries Ltd.(XD)  </Script>
    <Price> 100.74</Price>
  </Scripts>
  <Scripts>
    <Script>International Steels Limited. (XD)  </Script>
    <Price> 55.51</Price>
  </Scripts>
  <Scripts>
    <Script>Ittefaq Iron Industries Limited.  </Script>
    <Price> 7.26</Price>
  </Scripts>
  <Scripts>
    <Script>KSB Pumps Co Ltd.  </Script>
    <Price> 105.99</Price>
  </Scripts>
  <Scripts>
    <Script>Mughal Iron &amp; Steels Ind Ltd.  </Script>
    <Price> 67.77</Price>
  </Scripts>
</xml>